Workbook

Sheet 1st Page
A7: ANNEXURE-A
A8: Certificate from Financial Institution
A10: This is to certify that | C10: ='2nd Page'!E3 -> KHAKHI TEXTILES | F10: has been sanctioned | H10: Rs. | I10: ='2nd Page'!E4 -> 3044000/-
A11: term loan on Gross Fixed Capital Investment of Rs.1,39,89,000.00/- for the project located at PLOT NO.-30, OM TEXTILES PARK VIBHAG-10, PARAB,
A12: KAMREJ, SURAT. | F12: at the rate of 9.50% Interest.
A13: The unit has been disbursed total of Rs. 30,44,000.00 /- Upto. 06/11/2021 | H13: the first disbursement
A14: of the term loan of Rs. | D14: 30,44,000.00/- | E14: was disbursed on dt. | G14: 44506 | I14: and their
A15: term loan Account No. is | E15: ='2nd Page'!E5 -> 910000000013343
A17: The Unit had made repayment for the period dt | E17: ='2nd Page'!E7 -> 06/11/2021 TO 14/08/2025 | I17: as under
A19: Against Term Loan | C19: Rs. | D19: ='2nd Page'!F61 -> 3044000
A20: As Interest | C20: Rs. | D20: ='2nd Page'!N61 -> 901530
A21: Total | C21: Rs. | D21: =D19+D20 -> 3945530
A23: The interest subsidy @ 4%/ 4.5 %/ 5% / 6% on the amount disbursed for the period from | F23: =E17 -> 06/11/2021 TO 14/08/2025
A24: as per bank Rs. | C24: ='2nd Page'!K62 -> 530072 | D24: /-
A27: This is to Certify that penal intrest or other charges are not included in the said claim and the enterprise
A28: pays regular installments and intrest to the bank.
A30: The enterprise is not defaulter of the bank. | E30: ( In the case of defaulter, please give default period details )
F33: Signature Branch Manager
A34: Place : Surat.
A35: Date : | F35: Name of Bank
F37: Seal of the Bank

Sheet 2nd Page
A1: Name of the Bank / FI : | E1: SARASWAT CO-OPERATIVE BANK LTD.
A2: Branch : | E2: SURAT
A3: Name of the Unit : | E3: KHAKHI TEXTILES
A4: Term Loan Amount : | E4: 3044000/-
A5: Term Loan Account No: | E5: 910000000013343
A6: No. Of Installment | E6: 72 Month + 6 Moratorium Month
A7: Interest Subsidy Reimbursement Period : | E7: 06/11/2021 TO 14/08/2025
A8: CALCULATION SHEET
A11: Sr. No. | B11: Outstanding Principal amount brought forward (I.e closing principal balance(vide co.7 of the last claim submitted) (In Rupees) | C11: Disbursement during the Month | E11: Repayment (Actual Date Of Repayment Of principal amount only) during the month | G11: Principal amount outstanding (In Rupees) i.e. (Column 2 + Column 4 - Column 6 ) | H11: Number of days for which the balances utilised | K11: 6% interest reimbursement amount (In Rupees) i.e. 6% of (Column 7/365) X Column 10 | L11: Interest Payment Date | M11: ROI | N11: Interest Paid During the Period
A12: 1 | B12: 2 | C12: 3 | D12: 4 | E12: 5 | F12: 6 | G12: 7 | H12: 8 | I12: 9 | J12: 10 | K12: 11 | L12: 12 | M12: 13 | N12: 14 | Q12: =79136+702 -> 79838
C13: Date | D13: Amount (Rs.) | E13: Date | F13: Amount (Rs.) | H13: From Date | I13: To Date | J13: No. of Days | Q13: =702+78434+78434-79136 -> 78434
A14: 1 | B14: 0 | C14: 44506 | D14: 3044000 | G14: =B14+D14-F14 -> 3044000 | H14: =+C14 -> 44506 | I14: =H15-1 -> 44717 | J14: =I14-H14+1 -> 212 | K14: =ROUND(SUM(G14/365*J14*6/100),0) -> 106081 | L14: 44531 | M14: 9.5 | N14: 19807 | P14: =7.75+0.15 -> 7.9
A15: 2 | B15: =G14 -> 3044000 | E15: 44718 | F15: 42300 | G15: =B15+D15-F15 -> 3001700 | H15: =+E15 -> 44718 | I15: =H16-1 -> 44747 | J15: =I15-H15+1 -> 30 | K15: =ROUND(SUM(G15/365*J15*6/100),0) -> 14803 | L15: 44562 | M15: 9.5 | N15: 24560
A16: 3 | B16: =G15 -> 3001700 | E16: 44748 | F16: 42300 | G16: =B16+D16-F16 -> 2959400 | H16: =+E16 -> 44748 | I16: =H17-1 -> 44772 | J16: =I16-H16+1 -> 25 | K16: =ROUND(SUM(G16/365*J16*6/100),0) -> 12162 | L16: 44593 | M16: 9.5 | N16: 24561 | P16: =86100+800+86100 -> 173000
A17: 4 | B17: =G16 -> 2959400 | E17: 44773 | F17: 7 | G17: =B17+D17-F17 -> 2959393 | H17: =+E17 -> 44773 | I17: =H18-1 -> 44778 | J17: =I17-H17+1 -> 6 | K17: =ROUND(SUM(G17/365*J17*6/100),0) -> 2919 | L17: 44621 | M17: 9.5 | N17: 22184
A18: 5 | B18: =G17 -> 2959393 | E18: 44779 | F18: 42293 | G18: =B18+D18-F18 -> 2917100 | H18: =+E18 -> 44779 | I18: =H19-1 -> 44809 | J18: =I18-H18+1 -> 31 | K18: =ROUND(SUM(G18/365*J18*6/100),0) -> 14865 | L18: 44652 | M18: 9.5 | N18: 24560
A19: 6 | B19: =G18 -> 2917100 | E19: 44810 | F19: 42300 | G19: =B19+D19-F19 -> 2874800 | H19: =+E19 -> 44810 | I19: =H20-1 -> 44839 | J19: =I19-H19+1 -> 30 | K19: =ROUND(SUM(G19/365*J19*6/100),0) -> 14177 | L19: 44682 | M19: 9.5 | N19: 23775
A20: 7 | B20: =G19 -> 2874800 | E20: 44840 | F20: 42300 | G20: =B20+D20-F20 -> 2832500 | H20: =+E20 -> 44840 | I20: =H21-1 -> 44870 | J20: =I20-H20+1 -> 31 | K20: =ROUND(SUM(G20/365*J20*6/100),0) -> 14434 | L20: 44713 | M20: 9.5 | N20: 24748
A21: 8 | B21: =G20 -> 2832500 | E21: 44871 | F21: 42300 | G21: =B21+D21-F21 -> 2790200 | H21: =+E21 -> 44871 | I21: =H22-1 -> 44900 | J21: =I21-H21+1 -> 30 | K21: =ROUND(SUM(G21/365*J21*6/100),0) -> 13760 | L21: 44742 | M21: 9.5 | N21: 24769
A22: 9 | B22: =G21 -> 2790200 | E22: 44901 | F22: 42300 | G22: =B22+D22-F22 -> 2747900 | H22: =+E22 -> 44901 | I22: =H23-1 -> 44931 | J22: =I22-H22+1 -> 31 | K22: =ROUND(SUM(G22/365*J22*6/100),0) -> 14003 | L22: 44773 | M22: 9.5 | N22: 25822
A23: 10 | B23: =G22 -> 2747900 | E23: 44932 | F23: 42300 | G23: =B23+D23-F23 -> 2705600 | H23: =+E23 -> 44932 | I23: =H24-1 -> 44962 | J23: =I23-H23+1 -> 31 | K23: =ROUND(SUM(G23/365*J23*6/100),0) -> 13787 | L23: 44804 | M23: 9.5 | N23: 25454
A24: 11 | B24: =G23 -> 2705600 | E24: 44963 | F24: 42300 | G24: =B24+D24-F24 -> 2663300 | H24: =+E24 -> 44963 | I24: =H25-1 -> 44990 | J24: =I24-H24+1 -> 28 | K24: =ROUND(SUM(G24/365*J24*6/100),0) -> 12258 | L24: 44834 | M24: 9.5 | N24: 24279
A25: 12 | B25: =G24 -> 2663300 | E25: 44991 | F25: 42300 | G25: =B25+D25-F25 -> 2621000 | H25: =+E25 -> 44991 | I25: =H26-1 -> 45021 | J25: =I25-H25+1 -> 31 | K25: =ROUND(SUM(G25/365*J25*6/100),0) -> 13356 | L25: 44865 | M25: 9.5 | N25: 24718
A26: 13 | B26: =G25 -> 2621000 | E26: 45022 | F26: 42300 | G26: =B26+D26-F26 -> 2578700 | H26: =+E26 -> 45022 | I26: =H27-1 -> 45051 | J26: =I26-H26+1 -> 30 | K26: =ROUND(SUM(G26/365*J26*6/100),0) -> 12717 | L26: 44895 | M26: 9.5 | N26: 23566
A27: 14 | B27: =G26 -> 2578700 | E27: 45052 | F27: 42300 | G27: =B27+D27-F27 -> 2536400 | H27: =+E27 -> 45052 | I27: =H28-1 -> 45082 | J27: =I27-H27+1 -> 31 | K27: =ROUND(SUM(G27/365*J27*6/100),0) -> 12925 | L27: 44926 | M27: 9.5 | N27: 24621
A28: 15 | B28: =G27 -> 2536400 | E28: 45083 | F28: 42300 | G28: =B28+D28-F28 -> 2494100 | H28: =+E28 -> 45083 | I28: =H29-1 -> 45112 | J28: =I28-H28+1 -> 30 | K28: =ROUND(SUM(G28/365*J28*6/100),0) -> 12300 | L28: 44957 | M28: 9.5 | N28: 24764
... A53: 40 | B53: =G52 -> 1478900 | E53: 45844 | F53: 42300 | G53: =B53+D53-F53 -> 1436600 | H53: =+E53 -> 45844 | I53: =H54-1 -> 45882 | J53: =I53-H53+1 -> 39 | K53: =ROUND(SUM(G53/365*J53*6/100),0) -> 9210 | L53: 45716 | M53: 9.5 | N53: 12892
A54: 41 | B54: =G53 -> 1436600 | E54: 45883 | F54: =42300+1394300 -> 1436600 | G54: =B54+D54-F54 -> 0 | H54: =+E54 -> 45883 | I54: 45883 | J54: =I54-H54+1 -> 1 | K54: =ROUND(SUM(G54/365*J54*6/100),0) -> 0 | L54: 45747 | M54: 9.5 | N54: 13901
L55: 45777 | M55: 9.5 | N55: 13102
L56: 45808 | M56: 9.5 | N56: 13173
L57: 45838 | M57: 9.5 | N57: 12263
L58: 45869 | M58: 9.5 | N58: 12075
L59: 45883 | M59: 9.5 | N59: 4949
D61: =SUM(D14:D19) -> 3044000 | F61: =SUM(F14:F60) -> 3044000 | J61: =SUM(J14:J60) -> 1378 | N61: =SUM(N13:N60) -> 901530
A62: 6% Interest Subsidy as per Bank | K62: =SUM(K14:K61) -> 530072
A65: DATE | D65: BANK ROUND SEAL | G65: BANK MANAGER SIGN & STAMP

Sheet Sheet1
